LICENSE
MANIFEST.in
README.md
setup.py
django_groove.egg-info/PKG-INFO
django_groove.egg-info/SOURCES.txt
django_groove.egg-info/dependency_links.txt
django_groove.egg-info/top_level.txt
groove/__init__.py
groove/haystack_fields.py
groove/timezone.py
groove/auth/__init__.py
groove/auth/decorators.py
groove/context_processors/__init__.py
groove/context_processors/site.py
groove/email/__init__.py
groove/email/html.py
groove/http/__init__.py
groove/models/__init__.py
groove/models/abstract.py
groove/storage/__init__.py
groove/storage/s3.py
groove/views/__init__.py
groove/views/generic.py