Metadata-Version: 1.1
Name: django-groove
Version: 0.3.2
Summary: Various utilities for Django projects.
Home-page: https://github.com/funkbit/django-groove
Author: Funkbit
Author-email: post@funkbit.no
License: BSD
Platform: UNKNOWN
Classifier: Development Status :: 3 - Alpha
Classifier: Framework :: Django
Classifier: Intended Audience :: Developers
Classifier: License :: OSI Approved :: BSD License
Classifier: Programming Language :: Python
Classifier: Programming Language :: Python :: 2.6
Classifier: Programming Language :: Python :: 2.7
